ds4biz_format_parsers/__init__.py
ds4biz_format_parsers/apps/__init__.py
ds4biz_format_parsers/business/__init__.py
ds4biz_format_parsers/business/converters.py
ds4biz_format_parsers/business/text_extractors.py
ds4biz_format_parsers/config/__init__.py
ds4biz_format_parsers/config/app_config.py
ds4biz_format_parsers/dao/__init__.py
ds4biz_format_parsers/examples/__init__.py
ds4biz_format_parsers/model/__init__.py
ds4biz_format_parsers/model/emails.py
ds4biz_format_parsers/resources/__init__.py
ds4biz_format_parsers/services/__init__.py
ds4biz_format_parsers/test/__init__.py
ds4biz_format_parsers/test/test_email2textemail.py
ds4biz_format_parsers/utils/__init__.py
ds4biz_format_parsers/utils/email_utils.py
ds4biz_format_parsers-0.3.0.dist-info/METADATA
ds4biz_format_parsers-0.3.0.dist-info/WHEEL
ds4biz_format_parsers-0.3.0.dist-info/top_level.txt
ds4biz_format_parsers-0.3.0.dist-info/RECORD
