Metadata-Version: 2.1
Name: ds4biz-format-parsers
Version: 0.3.0
Author: Live Tech
Author-email: f.dantonio@ilivetech.it
Classifier: Programming Language :: Python :: 3
Classifier: License :: OSI Approved :: MIT License
Classifier: Operating System :: OS Independent
Requires-Python: >3.5.0
Requires-Dist: html2text
Requires-Dist: ds4biz-commons
